scrapy_mattermostbot-1.0.0.dist-info/METADATA
scrapy_mattermostbot-1.0.0.dist-info/WHEEL
scrapy_mattermostbot-1.0.0.dist-info/licenses/LICENSE
scrapymattermostbot/__init__.py
scrapymattermostbot/extensions.py
scrapy_mattermostbot-1.0.0.dist-info/RECORD
