Metadata-Version: 2.1
Name: scrapy-mattermostbot
Version: 1.0.0
Summary: A Scrapy extension for sending notification to Mattermost channels
Keywords: scrapy mattermost mattermostbot
Author-Email: Jeel Rupapara <zeelrupapara@gmail.com>
License: MIT
Requires-Python: >=3.6
Requires-Dist: scrapy
Requires-Dist: pdm
